psqlpy_piccolo/__init__.py
psqlpy_piccolo/engine.py
psqlpy_piccolo-0.1.7.dist-info/METADATA
psqlpy_piccolo-0.1.7.dist-info/WHEEL
psqlpy_piccolo-0.1.7.dist-info/RECORD
