Metadata-Version: 2.1
Name: psqlpy-piccolo
Version: 0.1.7
Summary: PSQLPy-based engine for Piccolo-orm
Keywords: python,postgresql,psqlpy,piccolo,async-engine,psqlpy-engine
Author: chandr-andr (Kiselev Aleksandr)
Author-email: chandr@chandr.net
Maintainer: Kiselev Aleksandr
Maintainer-email: chandr@chandr.net
Requires-Python: >=3.8,<4.0
Classifier: Development Status :: 4 - Beta
Classifier: Intended Audience :: Developers
Classifier: Operating System :: MacOS
Classifier: Operating System :: Microsoft
Classifier: Operating System :: POSIX :: Linux
Classifier: Programming Language :: Python
Classifier: Programming Language :: Python :: 3
Classifier: Programming Language :: Python :: 3.8
Classifier: Programming Language :: Python :: 3.9
Classifier: Programming Language :: Python :: 3.10
Classifier: Programming Language :: Python :: 3.11
Classifier: Programming Language :: Python :: 3.12
Classifier: Programming Language :: Python :: 3 :: Only
Classifier: Programming Language :: Rust
Classifier: Topic :: Database
Classifier: Typing :: Typed
Requires-Dist: piccolo (>=1.14.0,<2.0.0)
Requires-Dist: psqlpy (>=0.7.4,<0.8.0)
Requires-Dist: typing-extensions (>=4.12.2,<5.0.0)
